{"pk": "244861834", "username": "marcouderzo", "full_name": "Marco Uderzo", "is_private": false, "profile_pic_url": "https://scontent-mxp1-1.cdninstagram.com/v/t51.2885-19/288539776_3138124279787417_3138758548042918192_n.jpg?stp=dst-jpg_s150x150&_nc_ht=scontent-mxp1-1.cdninstagram.com&_nc_cat=105&_nc_ohc=K6Xa0PuuKU8AX_tl9wl&edm=ABfd0MgBAAAA&ccb=7-5&oh=00_AT_YKm5iDElN5FExrtDUz-I_1x0KT4ttHID9B6yIgpQODw&oe=62C15FEF&_nc_sid=7bff83", "profile_pic_url_hd": "https://scontent-mxp1-1.cdninstagram.com/v/t51.2885-19/288539776_3138124279787417_3138758548042918192_n.jpg?stp=dst-jpg_s320x320&_nc_ht=scontent-mxp1-1.cdninstagram.com&_nc_cat=105&_nc_ohc=K6Xa0PuuKU8AX_tl9wl&edm=ABfd0MgBAAAA&ccb=7-5&oh=00_AT9NWyA6Nr1ueTO5Deitla76GJfSnLeoHYJzYFohz-OrAw&oe=62C15FEF&_nc_sid=7bff83", "is_verified": false, "media_count": 31, "follower_count": 405, "following_count": 577, "biography": "\ud83c\uddee\ud83c\uddf9 1999, BdG/Pd \n\ud83d\udcda Informatica @unipd\n\ud83c\udfa8 Traditional & Digital Artist", "external_url": null, "account_type": null, "is_business": false, "public_email": null, "contact_phone_number": null, "public_phone_country_code": null, "public_phone_number": null, "business_contact_method": "UNKNOWN", "business_category_name": null, "category_name": null, "category": null, "address_street": null, "city_id": null, "city_name": null, "latitude": null, "longitude": null, "zip": null, "instagram_location_id": null, "interop_messaging_user_fbid": null}